README.md
setup.py
ufinder/__init__.py
ufinder/lprint.py
ufinder/ufinder.py
ufinder.egg-info/PKG-INFO
ufinder.egg-info/SOURCES.txt
ufinder.egg-info/dependency_links.txt
ufinder.egg-info/entry_points.txt
ufinder.egg-info/top_level.txt