Metadata-Version: 2.1
Name: ufinder
Version: 1.0.0
Summary: Search URL paths with UFinder.
Author: Jaedson Silva
Author-email: imunknowuser@protonmail.com
License: MIT
Project-URL: Source Code, https://github.com/jaedsonpys/ufinder
Project-URL: License, https://github.com/jaedsonpys/ufinder/blob/master/LICENSE
Platform: UNKNOWN
Classifier: Development Status :: 5 - Production/Stable
Classifier: Environment :: Console
Classifier: Intended Audience :: Information Technology
Classifier: License :: OSI Approved :: MIT License
Classifier: Natural Language :: English
Classifier: Operating System :: OS Independent
Classifier: Programming Language :: Python
Classifier: Topic :: Internet :: WWW/HTTP :: Indexing/Search
Classifier: Topic :: Security
